{
    "name": "mini Thread",
    "keywords": ["esp32", "thread", "mutex", "queue", "convar", "group", "signal", "workqueue"],
    "description": "Mini Thread is a library for creating secure threads for the esp32 microcontroller.  With variable condition support if required. And many other useful wrappers for the esp32 - mutex, semaphores and workqueues and etc",
    "authors":
    {
        "name": "RoseLeBlood",
		"email": "ambersophia.schroeck@outlook.com",
		"maintainer": true
    },
    "repository": 
    {
        "type": "git",
        "url": "https://github.com/RoseLeBlood/MiniThread.git"
    },
    "version": "1.95.1",
    "frameworks": "espidf",
    "platforms": "espressif32",
    "homepage": "https://roseleblood.github.io/mnthread-docs/index.html",
    "examples": [ "example/basic.ino" ]
}
